robobrowser/__init__.py
robobrowser/browser.py
robobrowser/cache.py
robobrowser/exceptions.py
robobrowser/helpers.py
robobrowser/responses.py
robobrowser/forms/__init__.py
robobrowser/forms/fields.py
robobrowser/forms/form.py
robobrowser_jmr-0.5.4a1.dist-info/LICENSE
robobrowser_jmr-0.5.4a1.dist-info/METADATA
robobrowser_jmr-0.5.4a1.dist-info/NOTICE
robobrowser_jmr-0.5.4a1.dist-info/WHEEL
robobrowser_jmr-0.5.4a1.dist-info/top_level.txt
robobrowser_jmr-0.5.4a1.dist-info/RECORD
