Metadata-Version: 2.1
Name: robobrowser-jmr
Version: 0.5.4a1
Summary: Your friendly neighborhood web scraper
Home-page: https://github.com/jackrosenthal/robobrowser
Author: Jack Rosenthal
Author-email: jack@rosenth.al
License: MIT
Keywords: robobrowser
Platform: UNKNOWN
Classifier: Development Status :: 2 - Pre-Alpha
Classifier: Intended Audience :: Developers
Classifier: License :: OSI Approved :: BSD License
Classifier: Natural Language :: English
Classifier: Programming Language :: Python :: 3
Classifier: Programming Language :: Python :: 3.6
Classifier: Programming Language :: Python :: 3.7
Classifier: Programming Language :: Python :: 3.8
Requires-Python: >=3.6, <4
Requires-Dist: beautifulsoup4 (>=4.3.2)
Requires-Dist: requests (>=2.6.0)
Requires-Dist: six (>=1.9.0)
Requires-Dist: Werkzeug (>=1.0.0)
